{
  "ACE": "Automated Commercial Environment",
  "AD": "Andorra",
  "AE": "United Arab Emirates",
  "AF": "Afghanistan",
  "AG": "Antigua and Barbuda",
  "AGC": "Agriculture",
  "AI": "Anguilla",
  "AL": "Albania",
  "AM": "Armenia",
  "ANSI": "The definitions coincide with the American National Standards Institute",
  "AO": "Angola",
  "APHIS": "Animal and Plant Health Inspection Service",
  "APTL": "Agriculture Programs and Trade Liaison",
  "AQI": "Agriculture Quarantine Inspection",
  "AQIM": "Agricultural Quarantine Inspection Monitoring",
  "AR": "Argentina",
  "ARM": "Entering information into the Agricultural Risk Management System",
  "AT": "Austria",
  "AU": "Australia",
  "AW": "Aruba",
  "AZ": "Azerbaijan",
  "BA": "Bosnia -Hercegovina",
  "BB": "Barbados",
  "BD": "Bangladesh",
  "BE": "Belgium",
  "BF": "Burkina",
  "BG": "Bulgaria",
  "BH": "Bahrain",
  "BI": "Burundi",
  "BJ": "Benin",
  "BM": "Bermuda",
  "BN": "Brunei Darussalam",
  "BO": "Bolivia",
  "BOL": "Bill of Lading",
  "BR": "Brazil",
  "BRASS": "Border Release Advance Screening and Selectivity",
  "BS": "Bahamas",
  "BSE": "Bovine Spongiform Encephalopathy",
  "BT": "Bhutan",
  "BW": "Botswana",
  "BY": "Byelarus",
  "BZ": "Belize",
  "CA": "Canada",
  "CBP": "Customs and Border Protection",
  "CBPAS": "CBP Agriculture Specialists",
  "CC": "Cocos (Keeling) Island",
  "CD": "(Kinshasa)",
  "CF": "Central African Republic",
  "CG": "Congo (Brazzaville)",
  "CH": "Switzerland",
  "CI": "Ivory Coast",
  "CK": "Cook Islands",
  "CL": "Chile",
  "CM": "Cameroon",
  "CN": "China",
  "CO": "Colombia",
  "CR": "Costa Rica",
  "CU": "Cuba",
  "CV": "Cape Verde",
  "CW": "Curacao",
  "CX": "Christmas Islands",
  "CY": "Cyprus",
  "CZ": "Czech Republic, The",
  "DE": "Germany, Federal Republic of",
  "DHS": "Department of Homeland Security",
  "DJ": "Djibouti",
  "DK": "Denmark",
  "DM": "Dominica",
  "DO": "Dominican Republic",
  "DZ": "Algeria",
  "EA": "Environmental Assessment",
  "EC": "Ecuador",
  "EE": "Estonia",
  "EG": "Egypt",
  "EIS": "Environmental Impact Statement",
  "EPA": "Environmental Protection Agency",
  "ER": "Eritrea",
  "ES": "Spanish Africa",
  "ET": "Ethiopia",
  "FDA": "Food and Drug Administration",
  "FI": "Finland",
  "FJ": "Fiji",
  "FK": "Falkland Islands (Malvinas)",
  "FM": "Micronesia, Federal States of",
  "FMD": "Foot and Mouth Disease",
  "FO": "Faroe Islands",
  "FR": "France",
  "FSIS": "Food Safety and Inspection Service",
  "GA": "Gabon",
  "GATT": "General Agreement on Tariffs and Trade",
  "GB": "United Kingdom",
  "GD": "Grenada",
  "GE": "Georgia",
  "GF": "French Guiana",
  "GH": "Ghana",
  "GI": "Gibraltar",
  "GL": "Greenland",
  "GM": "Gambia, The",
  "GN": "Guinea",
  "GP": "Guadeloupe",
  "GQ": "Equatorial Guinea",
  "GR": "Greece",
  "GT": "Guatemala",
  "GW": "Guinea -Bissau",
  "GY": "Guyana",
  "GZ": "Gaza Strip",
  "HK": "Hong Kong",
  "HM": "Heard Island and Mcdonald Islands",
  "HN": "Honduras",
  "HR": "Croatia",
  "HSUSA": "Harmonized System – United States of America",
  "HT": "Haiti",
  "HTS": "Harmonized Tariff Schedule",
  "HU": "Hungary",
  "ID": "Indonesia",
  "IE": "Ireland",
  "IL": "Israel",
  "IN": "India",
  "IPPC": "International Plant Protection Convention",
  "IQ": "Iraq",
  "IR": "Iran",
  "IS": "Iceland",
  "ISMU": "Information Services and Manuals Unit",
  "ISPM": "International Standards for Phytosanitary Measures",
  "IT": "Italy",
  "JM": "Jamaica",
  "JO": "Jordan",
  "JP": "Japan",
  "KE": "Kenya",
  "KG": "Kyrgyzstan",
  "KH": "Kampuchea,  Democratic",
  "KI": "Kiribati",
  "KM": "Comoros",
  "KN": "St. Kitts and Nevis",
  "KP": "North Korea",
  "KR": "South Korea",
  "KV": "Kosovo",
  "KW": "Kuwait",
  "KY": "Cayman Island",
  "KZ": "Kazakhstan",
  "LA": "Lao Peoples’ Democratic  Republic",
  "LACF": "Lacey Act Compliance Form",
  "LB": "Lebanon",
  "LC": "Saint Lucia",
  "LI": "Liechtenstein",
  "LK": "Sri Lanka",
  "LR": "Liberia",
  "LS": "Lesotho",
  "LT": "Lithuania",
  "LU": "Luxembourg",
  "LV": "Latvia",
  "LY": "Libya",
  "MA": "Morocco",
  "MC": "Monaco",
  "MCP": "Model Context Protocol",
  "MD": "Moldova",
  "ME": "Montenegro",
  "MG": "Madagascar",
  "MH": "Marshall Islands",
  "MK": "Macedonia, North",
  "ML": "Mali",
  "MM": "Burma (Myanmar)",
  "MN": "Mongolia",
  "MO": "Macau",
  "MQ": "Martinique",
  "MR": "Mauritania",
  "MS": "Montserrat",
  "MT": "Malta",
  "MU": "Mauritius",
  "MV": "Maldives",
  "MW": "Malawi",
  "MX": "Mexico",
  "MY": "Malaysia",
  "MZ": "Mozambique",
  "NA": "Namibia",
  "NAPPRA": "New Animal Products and Programs Risk Analysis",
  "NARP": "Commodities admissible under the National Agriculture Release Program",
  "NC": "New Caledonia",
  "NCIE": "National Center for Import and Export",
  "NE": "Niger",
  "NEPA": "National Environmental Policy Act",
  "NF": "Norfolk Island",
  "NG": "Nigeria",
  "NI": "Nicaragua",
  "NL": "Netherlands",
  "NO": "Norway",
  "NP": "Nepal",
  "NPPO": "National Plant Protection Organization",
  "NR": "Nauru",
  "NU": "Niue",
  "NZ": "New Zealand",
  "OM": "Oman",
  "PA": "Panama",
  "PE": "Peru",
  "PF": "French Polynesia",
  "PG": "Papua New Guinea",
  "PH": "Philippines",
  "PK": "Pakistan",
  "PL": "Poland",
  "PM": "St. Pierre and Miquelon",
  "PN": "Pitcairn Island",
  "PPQ": "Plant Protection and Quarantine",
  "PR": "Puerto Rico",
  "PRA": "Pest Risk Assessment",
  "PT": "Portugal",
  "PW": "Palau",
  "PY": "Paraguay",
  "QA": "Qatar",
  "RBS": "Risk Based Sampling",
  "RE": "Reunion",
  "RO": "Romania",
  "RS": "Serbia",
  "RU": "Russia",
  "RW": "Rwanda",
  "SA": "Saudi Arabia",
  "SB": "Solomon Islands",
  "SC": "Seychelles",
  "SD": "Sudan",
  "SE": "Sweden",
  "SG": "Singapore",
  "SH": "St. Helena",
  "SI": "Slovenia",
  "SITC": "Standard International Trade Classification",
  "SJ": "Svalvard and Jan Mayen Islands",
  "SK": "Slovakia",
  "SL": "Sierra Leone",
  "SM": "San Marino",
  "SN": "Senegal",
  "SO": "Somalia",
  "SPS": "The Agreement on Sanitary and Phytosanitary",
  "SR": "Suriname",
  "SS": "South Sudan",
  "ST": "Sao Tome and Principe",
  "SV": "El Salvador",
  "SWP": "Which commodities involved solid wood packaging",
  "SX": "Sint Maarten",
  "SY": "Syrian Arab Republic",
  "SZ": "Eswatini",
  "TBT": "Technical Barriers to Trade",
  "TC": "Turks and Caicos Island",
  "TD": "Chad",
  "TF": "French Southern and Antartic Lands",
  "TG": "Togo",
  "TH": "Thailand",
  "TJ": "Tajikistan",
  "TK": "Tokelau",
  "TL": "Timor -Leste",
  "TM": "Turkmenistan",
  "TN": "Tunisia",
  "TO": "Tonga",
  "TR": "Turkey",
  "TT": "Trinidad and Tobago",
  "TV": "Tuvalu",
  "TW": "Taiwan",
  "TZ": "Tanzania, United Republic of",
  "UA": "Ukraine",
  "UDR": "User Defined Rules",
  "UG": "Uganda",
  "UM": "United States Minor Outlying Islands",
  "US": "United States",
  "USDA": "United States Department of Agriculture",
  "USMCA": "United States-Mexico-Canada Agreement",
  "UY": "Uruguay",
  "UZ": "Uzbekistan",
  "VA": "Vatican City",
  "VC": "Saint Vincent and the Grenadines",
  "VE": "Venezuela",
  "VG": "British Virgin Islands",
  "VI": "Virgin Islands of the United States",
  "VN": "Viet Nam",
  "VS": "Veterinary Services",
  "VU": "Vanuatu",
  "WE": "West Bank",
  "WF": "Wallis and Futuna Islands",
  "WPM": "Wood Packaging Material",
  "WS": "Western Samoa",
  "WTO": "World Trade Organization",
  "YE": "Yemen, Republic of",
  "YT": "Mayotte",
  "ZA": "South Africa",
  "ZM": "Zambia",
  "ZW": "Zimbabwe"
}